qube/__init__.py
qube/qube_cli.py
qube/bump_version/__init__.py
qube/bump_version/bump_version.py
qube/common/__init__.py
qube/common/levensthein_dist.py
qube/common/load_yaml.py
qube/common/suggest_similar_commands.py
qube/common/version.py
qube/config/__init__.py
qube/config/config.py
qube/create/TemplateCreator.py
qube/create/__init__.py
qube/create/create.py
qube/create/github_support.py
qube/create/domains/CliCreator.py
qube/create/domains/GuiCreator.py
qube/create/domains/LibCreator.py
qube/create/domains/PortletCreator.py
qube/create/domains/QubeTemplateStruct.py
qube/create/domains/ServiceCreator.py
qube/create/domains/__init__.py
qube/create/templates/available_templates.yml
qube/create/templates/cli/cli_java/cookiecutter.json
qube/create/templates/cli/cli_java/{{ cookiecutter.project_slug }}/README.rst
qube/create/templates/cli/cli_java/{{ cookiecutter.project_slug }}/pom.xml
qube/create/templates/cli/cli_java/{{ cookiecutter.project_slug }}/qube.cfg
qube/create/templates/cli/cli_java/{{ cookiecutter.project_slug }}/.github/workflows/build_package.yml
qube/create/templates/cli/cli_java/{{ cookiecutter.project_slug }}/.github/workflows/dependabot.yml
qube/create/templates/cli/cli_java/{{ cookiecutter.project_slug }}/.github/workflows/java_checkstyle.yml
qube/create/templates/cli/cli_java/{{ cookiecutter.project_slug }}/docs/installation.rst
qube/create/templates/cli/cli_java/{{ cookiecutter.project_slug }}/docs/usage.rst
qube/create/templates/cli/cli_java/{{ cookiecutter.project_slug }}/src/main/java/life/qbic/cli/{{ cookiecutter.main_class_prefix }}Command.java
qube/create/templates/cli/cli_java/{{ cookiecutter.project_slug }}/src/main/java/life/qbic/cli/{{ cookiecutter.main_class_prefix }}EntryPoint.java
qube/create/templates/cli/cli_java/{{ cookiecutter.project_slug }}/src/main/java/life/qbic/cli/{{ cookiecutter.main_class_prefix }}Tool.java
qube/create/templates/cli/cli_java/{{ cookiecutter.project_slug }}/src/main/resources/log4j2.xml
qube-2.6.1.dist-info/AUTHORS.rst
qube-2.6.1.dist-info/LICENSE
qube-2.6.1.dist-info/METADATA
qube-2.6.1.dist-info/WHEEL
qube-2.6.1.dist-info/entry_points.txt
qube-2.6.1.dist-info/top_level.txt
qube-2.6.1.dist-info/RECORD
