Metadata-Version: 2.1
Name: qube
Version: 2.6.1
Summary: QBiC's internal project template collection.
Home-page: https://github.com/qbicsoftware/qube
Author: Lukas Heumos
Author-email: lukas.heumos@posteo.net
License: MIT
Keywords: qube
Platform: UNKNOWN
Classifier: Development Status :: 5 - Production/Stable
Classifier: Intended Audience :: Developers
Classifier: License :: OSI Approved :: MIT License
Classifier: Natural Language :: English
Classifier: Programming Language :: Python :: 3
Classifier: Programming Language :: Python :: 3.7
Classifier: Programming Language :: Python :: 3.8
Requires-Python: >=3.7
Requires-Dist: cookiecutter (==1.7.2)
Requires-Dist: click (==7.1.2)
Requires-Dist: ruamel.yaml (==0.16.12)
Requires-Dist: pygithub (==1.53)
Requires-Dist: GitPython (==3.1.9)
Requires-Dist: autopep8 (==1.5.4)
Requires-Dist: cffi (==1.14.3)
Requires-Dist: cryptography (==3.1.1)
Requires-Dist: requests (==2.24.0)
Requires-Dist: rich (==8.0.0)
Requires-Dist: packaging (==20.4)
Requires-Dist: appdirs (==1.4.4)
Requires-Dist: questionary (==1.7.0)
Requires-Dist: pynacl (==1.4.0)
